skimly/__init__.py
skimly/client.py
skimly/client_enhanced.py
skimly/errors.py
skimly/types.py
skimly/types_enhanced.py
skimly/utils.py
skimly/verify.py
skimly-2.0.3.dist-info/METADATA
skimly-2.0.3.dist-info/WHEEL
skimly-2.0.3.dist-info/RECORD
