Metadata-Version: 2.4
Name: skimly
Version: 2.0.3
Summary: Production-grade Python SDK for Skimly - AI token optimization with async streaming, tools, and full API coverage
Project-URL: Homepage, https://skimly.dev
Project-URL: Issues, https://github.com/skimly/skimly/issues
Author-email: Skimly <dev@skimly.dev>
License: MIT
Keywords: ai,anthropic,async,claude,compression,gateway,gpt,openai,sdk,skimly,streaming,tools
Classifier: Development Status :: 5 - Production/Stable
Classifier: Intended Audience :: Developers
Classifier: License :: OSI Approved :: MIT License
Classifier: Programming Language :: Python :: 3
Classifier: Programming Language :: Python :: 3.8
Classifier: Programming Language :: Python :: 3.9
Classifier: Programming Language :: Python :: 3.10
Classifier: Programming Language :: Python :: 3.11
Classifier: Programming Language :: Python :: 3.12
Classifier: Topic :: Software Development :: Libraries :: Python Modules
Requires-Python: >=3.8
Requires-Dist: httpx>=0.24.0
Requires-Dist: typing-extensions>=4.0.0
Provides-Extra: dev
Requires-Dist: black; extra == 'dev'
Requires-Dist: flake8; extra == 'dev'
Requires-Dist: pytest; extra == 'dev'
Requires-Dist: pytest-asyncio; extra == 'dev'
